pygen_modules/__init__.py
pygen_modules/crud_template.py
pygen_modules/formdata_template.py
pygen_modules/installer.py
pygen_modules-1.0.1.dist-info/METADATA
pygen_modules-1.0.1.dist-info/WHEEL
pygen_modules-1.0.1.dist-info/entry_points.txt
pygen_modules-1.0.1.dist-info/top_level.txt
pygen_modules-1.0.1.dist-info/RECORD
