Metadata-Version: 2.4
Name: pygen-modules
Version: 1.0.1
Summary: Generate CRUD and FormData boilerplate
Author: Manikandan
Requires-Python: >=3.8
Dynamic: author
Dynamic: requires-python
Dynamic: summary
